AUTHORS
CHANGES
LICENSE
MANIFEST.in
README.rst
VERSION
setup.py
pyhdb/__init__.py
pyhdb/auth.py
pyhdb/cesu8.py
pyhdb/compat.py
pyhdb/connection.py
pyhdb/cursor.py
pyhdb/exceptions.py
pyhdb.egg-info/PKG-INFO
pyhdb.egg-info/SOURCES.txt
pyhdb.egg-info/dependency_links.txt
pyhdb.egg-info/not-zip-safe
pyhdb.egg-info/top_level.txt
pyhdb/lib/__init__.py
pyhdb/lib/stringlib.py
pyhdb/lib/tracing.py
pyhdb/protocol/__init__.py
pyhdb/protocol/headers.py
pyhdb/protocol/lobs.py
pyhdb/protocol/message.py
pyhdb/protocol/parts.py
pyhdb/protocol/segments.py
pyhdb/protocol/types.py
pyhdb/protocol/constants/__init__.py
pyhdb/protocol/constants/function_codes.py
pyhdb/protocol/constants/general.py
pyhdb/protocol/constants/message_types.py
pyhdb/protocol/constants/parameter_direction.py
pyhdb/protocol/constants/part_kinds.py
pyhdb/protocol/constants/segment_kinds.py
pyhdb/protocol/constants/type_codes.py