Metadata-Version: 1.1
Name: pyhdb
Version: 0.3.4
Summary: SAP HANA Database Client for Python
Home-page: https://github.com/SAP/pyhdb
Author: Christoph Heer
Author-email: christoph.heer@sap.com
License: Apache License Version 2.0
Download-URL: https://github.com/SAP/PyHDB/tarball/0.2.1
Platform: UNKNOWN
Classifier: Development Status :: 4 - Beta
Classifier: Intended Audience :: Developers
Classifier: License :: OSI Approved :: Apache Software License
Classifier: Operating System :: OS Independent
Classifier: Programming Language :: Python :: 2.6
Classifier: Programming Language :: Python :: 2.7
Classifier: Programming Language :: Python :: 3.3
Classifier: Programming Language :: Python :: 3.4
Classifier: Programming Language :: Python :: Implementation :: PyPy
Classifier: Programming Language :: SQL
Classifier: Topic :: Database
Classifier: Topic :: Database :: Front-Ends
Classifier: Topic :: Software Development
Classifier: Topic :: Software Development :: Libraries :: Python Modules
